{"summaries":[{"symbol":{"__symbol":0},"metadata":{"__symbolic":"class"},"type":{"summaryKind":2,"type":{"reference":{"__symbol":0},"diDeps":[],"lifecycleHooks":[]},"entryComponents":[],"providers":[{"provider":{"token":{"identifier":{"reference":{"__symbol":3}}},"useClass":null,"useFactory":{"reference":{"__symbol":1},"diDeps":[{"isAttribute":false,"isHost":false,"isSelf":false,"isSkipSelf":false,"isOptional":false,"token":{"identifier":{"reference":{"__symbol":4}}}},{"isAttribute":false,"isHost":false,"isSelf":false,"isSkipSelf":false,"isOptional":false,"token":{"identifier":{"reference":{"__symbol":5}}}},{"isAttribute":false,"isHost":false,"isSelf":false,"isSkipSelf":false,"isOptional":false,"token":{"identifier":{"reference":{"__symbol":6}}}}]},"useExisting":null,"deps":[{"isAttribute":false,"isHost":false,"isSelf":false,"isSkipSelf":false,"isOptional":false,"token":{"identifier":{"reference":{"__symbol":4}}}},{"isAttribute":false,"isHost":false,"isSelf":false,"isSkipSelf":false,"isOptional":false,"token":{"identifier":{"reference":{"__symbol":5}}}},{"isAttribute":false,"isHost":false,"isSelf":false,"isSkipSelf":false,"isOptional":false,"token":{"identifier":{"reference":{"__symbol":6}}}}],"multi":false},"module":{"reference":{"__symbol":0},"diDeps":[],"lifecycleHooks":[]}},{"provider":{"token":{"identifier":{"reference":{"__symbol":2}}},"useClass":null,"useFactory":null,"useExisting":{"identifier":{"reference":{"__symbol":3}}},"multi":false},"module":{"reference":{"__symbol":0},"diDeps":[],"lifecycleHooks":[]}}],"modules":[{"reference":{"__symbol":0},"diDeps":[],"lifecycleHooks":[]}],"exportedDirectives":[],"exportedPipes":[]}},{"symbol":{"__symbol":1},"metadata":{"__symbolic":"function","parameters":["httpInterceptors","connectionBackend","requestOptions"],"value":{"__symbolic":"new","expression":{"__symbol":2},"arguments":[{"__symbolic":"reference","name":"httpInterceptors"},{"__symbolic":"reference","name":"connectionBackend"},{"__symbolic":"reference","name":"requestOptions"}]}}}],"symbols":[{"__symbol":0,"name":"InterceptorModule","filePath":"/home/giovanni/Projects/atende/angular-http-interceptor/src/interceptor.module.d.ts"},{"__symbol":1,"name":"httpFactory","filePath":"/home/giovanni/Projects/atende/angular-http-interceptor/src/interceptor.module.d.ts"},{"__symbol":2,"name":"CustomHttp","filePath":"/home/giovanni/Projects/atende/angular-http-interceptor/src/custom-http.d.ts"},{"__symbol":3,"name":"Http","filePath":"/home/giovanni/Projects/atende/angular-http-interceptor/node_modules/@angular/http/src/http.d.ts"},{"__symbol":4,"name":"Interceptor","filePath":"/home/giovanni/Projects/atende/angular-http-interceptor/src/interfaces.d.ts"},{"__symbol":5,"name":"XHRBackend","filePath":"/home/giovanni/Projects/atende/angular-http-interceptor/node_modules/@angular/http/src/backends/xhr_backend.d.ts"},{"__symbol":6,"name":"RequestOptions","filePath":"/home/giovanni/Projects/atende/angular-http-interceptor/node_modules/@angular/http/src/base_request_options.d.ts"}]}